netstrength.py
netstrength-1.0.0.dist-info/licenses/LICENSE
netstrength-1.0.0.dist-info/METADATA
netstrength-1.0.0.dist-info/WHEEL
netstrength-1.0.0.dist-info/entry_points.txt
netstrength-1.0.0.dist-info/top_level.txt
netstrength-1.0.0.dist-info/RECORD
