Metadata-Version: 2.4
Name: netstrength
Version: 1.0.0
Summary: Beautiful network quality analyzer with real-world usage estimates
Author: chibokocl
License-Expression: MIT
Project-URL: Homepage, https://github.com/chibokocl/netstrength
Project-URL: Repository, https://github.com/chibokocl/netstrength
Project-URL: Issues, https://github.com/chibokocl/netstrength/issues
Keywords: network,ping,latency,monitoring,cli,terminal
Classifier: Development Status :: 4 - Beta
Classifier: Environment :: Console
Classifier: Intended Audience :: Developers
Classifier: Intended Audience :: System Administrators
Classifier: Operating System :: OS Independent
Classifier: Programming Language :: Python :: 3
Classifier: Programming Language :: Python :: 3.9
Classifier: Programming Language :: Python :: 3.10
Classifier: Programming Language :: Python :: 3.11
Classifier: Programming Language :: Python :: 3.12
Classifier: Topic :: System :: Networking :: Monitoring
Classifier: Topic :: Utilities
Requires-Python: >=3.9
License-File: LICENSE
Dynamic: license-file
